[
  "Середній 2",
  {
    "ua": "гравець",
    "ru": "игрок",
    "en": "player",
    "fr": "le jouer",
    "opts": {
      "type": "Іменник",
      "sex": {
        "fr": "Чоловічий"
      },
      "singular": true,
      "desc": ""
    }
  },
  {
    "ua": "атлет",
    "ru": "атлет",
    "en": "athlete",
    "fr": "l'athlète",
    "opts": {
      "type": "Іменник",
      "sex": {
        "fr": "Чоловічий"
      },
      "singular": true,
      "desc": ""
    }
  },
  {
    "ua": "бігун",
    "ru": "бегун",
    "en": "runner",
    "fr": "le coureur",
    "opts": {
      "type": "Іменник",
      "sex": {
        "fr": "Чоловічий"
      },
      "singular": true,
      "desc": ""
    }
  },
  {
    "ua": "плавець",
    "ru": "плавец",
    "en": "swimmer",
    "fr": "la nageur",
    "opts": {
      "type": "Іменник",
      "sex": {
        "fr": "Чоловічий"
      },
      "singular": true,
      "desc": ""
    }
  },



  "Середній 3",
  {
    "ua": "спортсмен",
    "ru": "спортсмен",
    "en": "sportsman",
    "fr": "le sportif",
    "opts": {
      "type": "Іменник",
      "sex": {
        "fr": "Чоловічий"
      },
      "singular": true,
      "desc": ""
    }
  },
  {
    "ua": "вершник",
    "ru": "наездник",
    "en": "rider",
    "fr": "le cavalier",
    "opts": {
      "type": "Іменник",
      "sex": {
        "fr": "Чоловічий"
      },
      "singular": true,
      "desc": ""
    }
  },
  {
    "ua": "велосипедист",
    "ru": "велосипедист",
    "en": "cyclist",
    "fr": "le cycliste",
    "opts": {
      "type": "Іменник",
      "sex": {
        "fr": "Чоловічий"
      },
      "singular": true,
      "desc": ""
    }
  },
  {
    "ua": "боксер",
    "ru": "боксер",
    "en": "boxer",
    "fr": "le boxeur",
    "opts": {
      "type": "Іменник",
      "sex": {
        "fr": "Чоловічий"
      },
      "singular": true,
      "desc": ""
    }
  },



  "Поглиблений 1",
  {
    "ua": "футболіст",
    "ru": "футболист",
    "en": "football player",
    "fr": "le footballeur",
    "opts": {
      "type": "Іменник",
      "sex": {
        "fr": "Чоловічий"
      },
      "singular": true,
      "desc": ""
    }
  },
  {
    "ua": "баскетболіст",
    "ru": "баскетболист",
    "en": "basketball player",
    "fr": "le joueur de basket",
    "opts": {
      "type": "Іменник",
      "sex": {
        "fr": "Чоловічий"
      },
      "singular": true,
      "desc": ""
    }
  },
  {
    "ua": "волейболіст",
    "ru": "волейболист",
    "en": "volleyballer",
    "fr": "le joueur de volley",
    "opts": {
      "type": "Іменник",
      "sex": {
        "fr": "Чоловічий"
      },
      "singular": true,
      "desc": ""
    }
  },
  {
    "ua": "тенісист",
    "ru": "теннисист",
    "en": "tennis player",
    "fr": "le joueur de tennis",
    "opts": {
      "type": "Іменник",
      "sex": {
        "fr": "Чоловічий"
      },
      "singular": true,
      "desc": ""
    }
  },



  "Поглиблений 2",
  {
    "ua": "жокей",
    "ru": "жокей",
    "en": "jockey",
    "fr": "le jockey",
    "opts": {
      "type": "Іменник",
      "sex": {
        "fr": "Чоловічий"
      },
      "singular": true,
      "desc": ""
    }
  },
  {
    "ua": "лижник",
    "ru": "лыжник",
    "en": "skier",
    "fr": "le skieur",
    "opts": {
      "type": "Іменник",
      "sex": {
        "fr": "Чоловічий"
      },
      "singular": true,
      "desc": ""
    }
  },
  {
    "ua": "гольфіст",
    "ru": "гольфист",
    "en": "golfer",
    "fr": "le golfeur",
    "opts": {
      "type": "Іменник",
      "sex": {
        "fr": "Чоловічий"
      },
      "singular": true,
      "desc": ""
    }
  },
  {
    "ua": "хокеїст",
    "ru": "хокеист",
    "en": "ice hockey player",
    "fr": "le joueur de hockey",
    "opts": {
      "type": "Іменник",
      "sex": {
        "fr": "Чоловічий"
      },
      "singular": true,
      "desc": ""
    }
  }
]
